indy_bls/__init__.py
indy_bls/bls.py
indy_bls/error.py
indy_bls/lib.py
indy_bls/libindy_blssignatures.so
indy_bls-0.1.0.dist-info/LICENSE
indy_bls-0.1.0.dist-info/METADATA
indy_bls-0.1.0.dist-info/WHEEL
indy_bls-0.1.0.dist-info/top_level.txt
indy_bls-0.1.0.dist-info/RECORD
