Metadata-Version: 2.1
Name: indy-bls
Version: 0.1.0
Summary: Python wrapper for the Indy BLS signatures implementation
Home-page: https://github.com/hyperledger/indy-bls-wrapper-python
Author: Andrew Whitehead, Berend Sliedrecht, Stephen Curran
Author-email: cywolf@gmail.com, berend@animo.id, swcurran@cloudcompass.ca
License: Apache-2.0
Platform: UNKNOWN
Classifier: Programming Language :: Python :: 3
Classifier: License :: OSI Approved :: Apache Software License
Classifier: Operating System :: OS Independent
Requires-Python: >=3.6.3
